setup.py
hycc/__init__.py
hycc/util.hy
hycc.egg-info/PKG-INFO
hycc.egg-info/SOURCES.txt
hycc.egg-info/dependency_links.txt
hycc.egg-info/entry_points.txt
hycc.egg-info/requires.txt
hycc.egg-info/top_level.txt
hycc/core/__init__.hy
hycc/core/build.hy
hycc/core/shadow.hy
hycc/core/translate.hy