Metadata-Version: 1.1
Name: hycc
Version: 0.1.3
Summary: HyCC - A static compiler for Hy
Home-page: https://github.com/koji-kojiro/hylang-hycc
Author: koji-kojiro
Author-email: kojiro0531@gmail.com
License: MIT
Platform: UNKNOWN
Classifier: Operating System :: POSIX
Classifier: Operating System :: MacOS
Classifier: Intended Audience :: Developers
Classifier: Programming Language :: Lisp
Classifier: Programming Language :: Python
Classifier: Programming Language :: Python :: 2
Classifier: Programming Language :: Python :: 2.7
Classifier: Programming Language :: Python :: 3
Classifier: Programming Language :: Python :: 3.3
Classifier: Programming Language :: Python :: 3.4
Classifier: Programming Language :: Python :: 3.5
Classifier: Topic :: Software Development :: Code Generators
Classifier: Topic :: Software Development :: Compilers
Classifier: License :: OSI Approved :: MIT License
Classifier: Development Status :: 4 - Beta
